tdm/__init__.py
tdm/client.py
tdm/version.py
eratos_tdm-2.33.1.dist-info/METADATA
eratos_tdm-2.33.1.dist-info/WHEEL
eratos_tdm-2.33.1.dist-info/licenses/LICENSE
eratos_tdm-2.33.1.dist-info/RECORD
